[
    {
        "image": "level2/C_Logo.png",
        "name": "C"
    },
    {
        "image": "level2/c#.png",
        "name": "c#"
    },
    {
        "image": "level2/c++.png",
        "name": "c++"
    },
    {
        "image": "level2/c#.png",
        "name": "css"
    },
    {
        "image": "level2/go.png",
        "name": "go"
    },
    {
        "image": "level2/html.png",
        "name": "html"
    },
    {
        "image": "level2/j.png",
        "name": "java"
    },
    {
        "image": "level2/js.png",
        "name": "js"
    },
    {
        "image": "level2/php.png",
        "name": "php"
    },
    {
        "image": "level2/py.png",
        "name": "py"
    },
    {
        "image": "level2/sql.png",
        "name": "sql"
    },
    {
        "image": "level2/xml.png",
        "name": "xml"
    },
    {
        "image": "level2/ruby.png",
        "name": "ruby"
    }
]